lattice/__init__.py
lattice/api/__init__.py
lattice/api/accounts/__init__.py
lattice/api/accounts/get_api_v1_account.py
lattice/api/accounts/get_api_v1_account_statement.py
lattice/api/accounts/get_api_v1_account_transactions.py
lattice/api/accounts/post_api_v1_account_deposit.py
lattice/api/accounts/post_api_v1_account_withdraw.py
lattice/api/admin/__init__.py
lattice/api/admin/get_api_v1_admin_alerts.py
lattice/api/admin/get_api_v1_admin_alerts_stats.py
lattice/api/admin/get_api_v1_admin_audit.py
lattice/api/admin/get_api_v1_admin_audit_export.py
lattice/api/admin/get_api_v1_admin_audit_resources_type_id.py
lattice/api/admin/get_api_v_1_admin_alerts_alert_id.py
lattice/api/admin/get_api_v_1_admin_audit_audit_id.py
lattice/api/admin/get_api_v_1_admin_audit_users_user_id.py
lattice/api/admin/patch_api_v_1_admin_alerts_alert_id.py
lattice/api/admin/post_api_v_1_admin_alerts_alert_id_resolve.py
lattice/api/api_keys/__init__.py
lattice/api/api_keys/delete_api_v_1_admin_api_keys_key_id.py
lattice/api/api_keys/delete_api_v_1_api_keys_key_id.py
lattice/api/api_keys/get_api_v1_admin_api_keys.py
lattice/api/api_keys/get_api_v1_api_keys.py
lattice/api/api_keys/post_api_v1_api_keys.py
lattice/api/api_keys/post_api_v_1_api_keys_key_id_rotate.py
lattice/api/docs/__init__.py
lattice/api/docs/get_openapi_json.py
lattice/api/docs/get_openapi_yaml.py
lattice/api/docs/get_redoc.py
lattice/api/health/__init__.py
lattice/api/health/get_health.py
lattice/api/health/get_health_live.py
lattice/api/health/get_health_metrics.py
lattice/api/health/get_health_ready.py
lattice/api/markets/__init__.py
lattice/api/markets/get_api_v1_markets.py
lattice/api/markets/get_api_v_1_markets_market_id.py
lattice/api/markets/get_api_v_1_markets_market_id_orderbook.py
lattice/api/markets/get_api_v_1_markets_market_id_trades.py
lattice/api/markets/patch_api_v_1_markets_market_id.py
lattice/api/markets/post_api_v1_markets.py
lattice/api/markets/post_api_v_1_markets_market_id_activate.py
lattice_trading-0.1.0.dist-info/METADATA
lattice_trading-0.1.0.dist-info/WHEEL
lattice_trading-0.1.0.dist-info/RECORD
