Metadata-Version: 2.4
Name: lattice-trading
Version: 0.1.0
Summary: A client library for accessing the Lattice Prediction Market API
Requires-Python: >=3.9,<4.0
Classifier: Programming Language :: Python :: 3
Classifier: Programming Language :: Python :: 3.9
Classifier: Programming Language :: Python :: 3.10
Classifier: Programming Language :: Python :: 3.11
Classifier: Programming Language :: Python :: 3.12
Classifier: Programming Language :: Python :: 3.13
Classifier: Programming Language :: Python :: 3.14
Requires-Dist: attrs (>=21.3.0)
Requires-Dist: httpx (>=0.20.0,<0.28.0)
Requires-Dist: pydantic (>=2.0.0,<3.0.0)
Requires-Dist: python-dateutil (>=2.8.0,<3.0.0)
